<DOMSymbolItem xmlns:xsi="http://www.w3.org/2001/XMLSchema-instance" xmlns="http://ns.adobe.com/xfl/2008/" name="outro/Symbol 8" itemID="64417ebd-00000212" lastModified="1682014402">
  <timeline>
    <DOMTimeline name="Symbol 8" layerDepthEnabled="true">
      <layers>
        <DOMLayer name="Layer_1" color="#00FFFF" current="true" isSelected="true" heightLiteral="32">
          <frames>
            <DOMFrame index="0" keyMode="9728">
              <elements>
                <DOMShape>
                  <fills>
                    <FillStyle index="1">
                      <SolidColor color="#23201F"/>
                    </FillStyle>
                    <FillStyle index="2">
                      <SolidColor color="#5E484D"/>
                    </FillStyle>
                    <FillStyle index="3">
                      <SolidColor color="#886A6A"/>
                    </FillStyle>
                  </fills>
                  <edges>
                    <Edge fillStyle1="1" edges="!1975 -9768|1992 -10080!1992 -10080|2120 -10074!2120 -10074[2130 -9706 2058 -9343!2058 -9343[1888 -8483 1852 -7603!1852 -7603[1832 -7113 1861 -6624!1861 -6624[1885 -6205 1947 -5785!1947 -5785[1982 -5552 2016 -5315!2016 -5315[2127 -4536
 2087 -3751!2087 -3751[2070 -3422 2033 -3099!2033 -3099[2023 -3009 2022 -2918!2022 -2918[2019 -2578 2056 -2237!2056 -2237[2122 -1626 2333 -1046!2333 -1046[#97D.3B -780.59375 2534 -520!2534 -520[#9FF.11 #FFFE36.A4 2584.5 -395!2584.5 -395
|2585 -395!2585 -395[#B3E.3D #FFFF7F.DB 3134.5 -198.5!3134.5 -198.5[#D3E.D2 #FFFEF3.02 3819 -208.5!3819 -208.5[#1097.1 #FFFF6C.23 4639 -165!4639 -165[#13A6.F8 #FFFF49.F6 5615 54!5615 54[5846 146 6057 271!6057 271[6261 394 6446 548!6446
 548[6655 720 6797 950!6797 950[7067 1389 7158 1896!7158 1896[7185 2046 7184 2197!7184 2197[7182 2376 7126 2548!7126 2548[6980 2999 6620 3310!6620 3310[6968 3265 7252 3450!7252 3450[7377 3532 7463 3657!7463 3657[7646 3920 7752 4228!7752
 4228[7806 4383 7859 4538!7859 4538[7905 4674 7950 4810!7950 4810[8000 4962 8042 5114!8042 5114[8159 5539 8131 5977!8131 5977[8116 6216 8045 6446!8045 6446[7976 6673 7877 6892!7877 6892[7682 7321 7428 7717!7428 7717[7355 7832 7246 7913
!7246 7913[6893 8180 6477 8314!6477 8314[6537 8972 6273 9573!6273 9573[6147 9858 5955 10101!5955 10101[5832 10256 5658 10354!5658 10354[5514 10434 5355 10482!5355 10482[5190 10534 5016 10562!5016 10562[4676 10610 4366 10491!4366 10491
[4075 10609 3781 10717!3781 10717[3693 10748 3595 10749!3595 10749[3591 10625 3670 10532!3670 10532[3805 10375 3889 10188!3889 10188[3884 10184 3880 10180!3880 10180[3781 10084 3690 9973!3690 9973[3596 9860 3538 9727!3538 9727[3324 9234
 3443 8708!3443 8708[3486 8518 3545 8335!3545 8335[3662 7976 3744 7615!3744 7615[3807 7336 3678 7080!3678 7080[3599 6921 3510 6764!3510 6764[3445 6649 3316 6617!3316 6617[3187 6589 3059 6568!3059 6568[2815 6535 2581 6452!2581 6452[2532
 6432 2457 6440!2457 6440[2235 6448 2013 6486!2013 6486[1931 6498 1850 6502!1850 6502[1551 6521 1251 6533!1251 6533[#371.51 #1993.B8 -145 6551!-145 6551|-145 6552!-145 6552[-202.5 #1998.04 -260 6552!-260 6552[#FFFEFA.A6 6552 -262.5 6551.5
!-262.5 6551.5|-405.5 6552!-405.5 6552[#FFFE46.DF #1997.F1 -477.5 6552!-477.5 6552|-479 6552!-479 6552[#FFF7AE.CB #1992.D6 -3079 6468!-3079 6468[-3731 6419 -4350 6615!-4350 6615[-4415 6637 -4477 6667!-4477 6667[-4489 6674 -4499 6685!-4499
 6685|-4628 6693!-4628 6693[-4906 7003 -4930 7408!-4930 7408[-4938 7545 -4857 7661!-4857 7661[-4705 7875 -4497 8035!-4497 8035[-4441 8077 -4392 8127!-4392 8127[-4353 8165 -4322 8208!-4322 8208[-4216 8362 -4188 8547!-4188 8547[#FFEFE0.0D
 #22EA.A4 -4268 9302.5!-4268 9302.5[#FFF017.0E #2474.12 -3877 9381!-3877 9381[-3884 9772 -4422 9929!-4422 9929[#FFEE53.9B #26E7.97 -4626 9993.5!-4626 9993.5[#FFED55.B8 #27CB.9D -5035 10225!-5035 10225[-5118 10237 -5203 10240!-5203 10240
[#FFEB52.D #2806.DD -5383.5 10252!-5383.5 10252|-5413 10258!-5413 10258[#FFEAD9.68 #280F.ED -5416 10254!-5416 10254[#FFE7F9.D8 #2836.3F -6882 10227!-6882 10227[-7039 10213 -7184 10155!-7184 10155[-7503 10031 -7804 9863!-7804 9863[-8042
 9730 -8189 9502!-8189 9502[-8383 9202 -8388 8845!-8388 8845[-8399 8035 -8073 7287!-8073 7287[-7661 6341 -6963 5582!-6963 5582[-6688 5283 -6327 5098!-6327 5098[-6234 4806 -6095 4534!-6095 4534[-5987 4324 -5950 4088!-5950 4088[-5922 3907
 -5899 3728!-5899 3728[-5882 3591 -5865 3455!-5865 3455[-5853 3360 -5838 3267!-5838 3267[-5789 2975 -5707 2688!-5707 2688[-5677 2583 -5649 2476!-5649 2476[-5639 2438 -5630 2400!-5630 2400[#FFEAA1.0F #72C.65 -5334 1443.5!-5334 1443.5[#FFEBB3.14
 #41A.94 -4979.5 655!-4979.5 655[-4762.125 #103.A -4677 -205!-4677 -205[#FFEE10.0B #FFFD62.1A -4499 -1368!-4499 -1368[-4433 -1867 -4352 -2364!-4352 -2364[-4337 -2455 -4351 -2551!-4351 -2551[-4435 -3111 -4432 -3676!-4432 -3676[-4430 -4063
 -4423 -4453!-4423 -4453[-4418 -4728 -4380 -5002!-4380 -5002[-4317 -5449 -4188 -5883!-4188 -5883[-4060 -6314 -3983 -6758!-3983 -6758[-3912 -7171 -3879 -7592!-3879 -7592[-3825 -8275 -3901 -8956!-3901 -8956[-3967 -9538 -4003 -10120!-4003
 -10120[-4023 -10434 -4005 -10749!-4005 -10749|-3898 -10743!-3898 -10743|-3878 -10431"/>
                    <Edge fillStyle0="1" fillStyle1="2" edges="
!1975 -9768|2081 -9758!2081 -9758|2080 -9632!2080 -9632|1959 -9640!1959 -9640[1843 -9037 1772 -8429!1772 -8429[1718 -7965 1711 -7497!1711 -7497[1705 -7047 1732 -6594!1732 -6594[1761 -6122 1816 -5658!1816 -5658[1845 -5408 1883 -5163!1883
 -5163[1955 -4704 1965 -4238!1965 -4238[1973 -3859 1933 -3481!1933 -3481|1890 -3483!1890 -3483[1878 -2945 1897 -2406!1897 -2406[1903 -2243 1920 -2080!1920 -2080[1933 -1954 1957 -1833!1957 -1833[1979 -1725 2006 -1617!2006 -1617[2062 -1390
 2131 -1167!2131 -1167[#8B8.2D #FFFCB7.94 2354 -520!2354 -520[#949.BA #FFFE36.9F 2402.5 -395!2402.5 -395|2403 -395!2403 -395|2693 -105!2693 -105|2958 22!2958 22[3456 -65 3980 -68!3980 -68[4093 -69 4206 -67!4206 -67[4297 -65 4388 -63!4388
 -63[4572 -54 4748 -27!4748 -27[4886 -4 5026 32!5026 32[5868 257 6488 859!6488 859[6716 1079 6837 1369!6837 1369[6999 1759 7023 2179!7023 2179[7043 2520 6839 2795!6839 2795[6611 3104 6293 3319!6293 3319[6033 3495 5740 3614!5740 3614[5065
 3888 4353 4027!4353 4027[3913 4112 3468 4139!3468 4139[3251 4156 3042 4136!3042 4136[3202 3275 2403 3275!2403 3275|2403 3243!2403 3243|2275 3238!2275 3238|2133 3287!2133 3287|2133 3404!2133 3404|2194 3416!2194 3416[2099 3583 2033 3751
!2033 3751[1921 3639 1853 3483!1853 3483[1763 3276 1828 3062!1828 3062[1931 2723 2241 2543!2241 2543[2662 2300 3140 2192!3140 2192[3549 2096 3964 2020!3964 2020|3961 1884!3961 1884[3061 1971 2241 2342!2241 2342[2141 2386 2047 2449!2047
 2449[1942 2520 1862 2613!1862 2613[1788 2697 1744 2801!1744 2801[1694 2922 1678 3053!1678 3053[1627 3475 1836 3830!1836 3830[1884 3911 1962 3964!1962 3964[1894 4211 1889 4463!1889 4463[2284 4353 2700 4323!2700 4323|2712 4355!2712 4355
[2778 4371 2846 4359!2846 4359[2892 4349 2931 4321!2931 4321[2962 4300 2989 4274!2989 4274[3385 4306 3781 4263!3781 4263[4507 4178 5212 3976!5212 3976[5479 3898 5743 3805!5743 3805[6128 3667 6461 3436!6461 3436[6727 3437 6982 3500!6982
 3500[7054 3515 7114 3559!7114 3559[7185 3612 7244 3680!7244 3680[7324 3774 7388 3879!7388 3879[7469 4012 7531 4154!7531 4154[7757 4670 7916 5206!7916 5206[8046 5645 7968 6091!7968 6091[7917 6387 7792 6659!7792 6659[7605 7067 7390 7463
!7390 7463[7314 7603 7197 7709!7197 7709[6864 8007 6439 8153!6439 8153[5971 8314 5484 8232!5484 8232[5353 8210 5234 8167!5234 8167[5238 8159 5241 8152!5241 8152[5533 7540 4907 7244!4907 7244[4875 7241 4844 7238!4844 7238[4727 7232 4624
 7293!4624 7293[4603 7305 4584 7318!4584 7318[4613 7152 4716 7008!4716 7008[4944 6690 5093 6335!5093 6335[5378 5654 5128 4971!5128 4971[5109 4920 5064 4892!5064 4892[4810 4741 4521 4692!4521 4692[4191 4632 3859 4653!3859 4653|3859 4765
!3859 4765[4374 4781 4851 4973!4851 4973[4909 4996 4955 5036!4955 5036[5025 5099 5057 5188!5057 5188[5097 5297 5105 5417!5105 5417[5116 5574 5098 5732!5098 5732[5032 6296 4664 6726!4664 6726[4453 6974 4424 7294!4424 7294[4417 7367 4420
 7439!4420 7439[4418 7440 4417 7441!4417 7441[4035 7776 3848 8141!3848 8141|4869 8189!4869 8189|4876 8223!4876 8223|4950 8226!4950 8226[5070 8288 5201 8331!5201 8331[5353 8381 5514 8386!5514 8386[5828 8399 6139 8381!6139 8381[6250 8373
 6355 8347!6355 8347[6364 8916 6140 9440!6140 9440[6058 9633 5949 9810!5949 9810[5875 9928 5779 10029!5779 10029[5707 10103 5622 10160!5622 10160[5524 10227 5421 10280!5421 10280[5020 10481 4614 10389!4614 10389[4706 10350 4797 10310
!4797 10310[4843 10079 4767 9894!4767 9894[4610 9512 4162 9621!4162 9621|3958 10005!3958 10005[3763 9801 3646 9540!3646 9540[3532 9288 3557 9011!3557 9011[3584 8714 3679 8432!3679 8432[3799 8076 3878 7709!3878 7709[3942 7413 3865 7124
!3865 7124[3805 6896 3689 6688!3689 6688[3588 6508 3386 6483!3386 6483[3362 6484 3340 6477!3340 6477[3213 6445 3086 6413!3086 6413|3218 6408!3218 6408[2973 6234 2676 6277!2676 6277[2597 6286 2518 6289!2518 6289[2391 6292 2263 6301!2263
 6301[2103 6312 1943 6338!1943 6338[1832 6359 1721 6380!1721 6380[1486 6395 1251 6405!1251 6405[824 6423 397 6424!397 6424[#FFFF35.81 #1918.24 -260 6424!-260 6424[-1860 6422 -2665 6360!-2665 6360[-2812 6350 -2961 6341!-2961 6341[-3081
 6334 -3197 6330!-3197 6330[-3285 6324 -3373 6323!-3373 6323[-3591 6321 -3811 6338!-3811 6338[-4197 6353 -4548 6497!-4548 6497|-4563 6467!-4563 6467[-4757 6461 -4857 6658!-4857 6658[-4888 6718 -4921 6777!-4921 6777[-4988 6899 -5025 7032
!-5025 7032[-5063 7167 -5073 7304!-5073 7304[-5081 7429 -5065 7553!-5065 7553[-5320 7465 -5518 7482!-5518 7482|-5517 7600!-5517 7600[-5258 7650 -5013 7747!-5013 7747[-4952 7889 -4825 7992!-4825 7992[-4656 8130 -4508 8289!-4508 8289[-4287
 8526 -4323 8843!-4323 8843[-4349 9069 -4431 9278!-4431 9278[#FFEEB0.78 #243F.5C -4432 9280.5!-4432 9280.5[#FFEC56.19 #23FD.2F -5626 9329!-5626 9329|-5634 9299!-5634 9299|-5763 9299!-5763 9299|-5770 9355!-5770 9355|-5852 9392!-5852 9392
|-5866 9525!-5866 9525|-5721 9563!-5721 9563[#FFE9E3.9B #268B.9 -5511.5 10114!-5511.5 10114[#FFE838.13 #27A6.33 -6666 10122!-6666 10122[-6894 10103 -7105 10011!-7105 10011[-7410 9879 -7701 9710!-7701 9710[-7895 9597 -8031 9421!-8031 9421
[-8201 9203 -8233 8927!-8233 8927[-8293 8413 -8127 7920!-8127 7920[-7794 6932 -7173 6090!-7173 6090[-6715 5469 -6018 5140!-6018 5140|-6024 4986!-6024 4986|-6105 5010!-6105 5010[-5882 4584 -5806 4107!-5806 4107[-5789 4002 -5775 3902!-5775
 3902[-5758 3773 -5743 3650!-5743 3650[-5733 3573 -5722 3496!-5722 3496[-5714 3446 -5703 3396!-5703 3396[-5605 2933 -5491 2473!-5491 2473[-5482 2437 -5473 2400!-5473 2400[#FFEC96.8D #3A2.E9 -4785.5 576!-4785.5 576[#FFEE06.3F #DD.21 -4471
 -609.5!-4471 -609.5[#FFEF0B.F1 #FFFA5F.F -4232 -2046!-4232 -2046|-4103 -2049!-4103 -2049[-4202 -2310 -4132 -2573!-4132 -2573|-4205 -2576!-4205 -2576[-4380 -3682 -4257 -4792!-4257 -4792[-4232 -5015 -4193 -5234!-4193 -5234[-4168 -5374
 -4132 -5507!-4132 -5507[-4100 -5630 -4066 -5755!-4066 -5755[-4027 -5899 -3986 -6048!-3986 -6048[-3756 -6870 -3740 -7728!-3740 -7728[-3727 -8429 -3780 -9131!-3780 -9131[-3814 -9590 -3850 -10053!-3850 -10053[-3858 -10162 -3867 -10271!-3867
 -10271|-3956 -10280!-3956 -10280|-3925 -10438!-3925 -10438|-3878 -10431"/>
                    <Edge fillStyle1="2" edges="
!-3878 -10431[-3415 -10363 -2950 -10322!-2950 -10322[-2434 -10276 -1919 -10252!-1919 -10252[-1401 -10238 -895 -10149!-895 -10149[-553 -10093 -214 -10029!-214 -10029[157 -9958 530 -9921!530 -9921[885 -9882 1240 -9843!1240 -9843[1607 -9806
 1975 -9768"/>
                    <Edge fillStyle0="1" fillStyle1="2" edges="
!2276 181|2392 152!2392 152|2337 136!2337 136|2276 181"/>
                    <Edge fillStyle0="3" fillStyle1="1" edges="
!2747 3472[2615 3389 2459 3416!2459 3416[2431 3418 2404 3421!2404 3421|2403 3501!2403 3501[2256 3660 2169 3862!2169 3862[2131 3950 2105 4046!2105 4046[2077 4147 2062 4257!2062 4257|2881 4129!2881 4129[2882 4122 2884 4115!2884 4115[2947
 3768 2747 3472!4839 7388[4720 7505 4596 7618!4596 7618[4532 7675 4468 7732!4468 7732[4320 7860 4164 7982!4164 7982[4138 8002 4109 8018!4109 8018|5000 8046!5000 8046|5006 8094!5006 8094|5081 8088!5081 8088[5344 7771 4998 7509!4998 7509
[4945 7469 4894 7428!4894 7428[4867 7407 4839 7388!4551 9834[4462 9739 4333 9756!4333 9756[4314 9759 4295 9762!4295 9762[4168 9930 4077 10117!4077 10117[4036 10200 4003 10286!4003 10286[3966 10378 3938 10475!3938 10475|4670 10202!4670
 10202[4708 9986 4551 9834!-4665 9805|-4140 9502!-4140 9502[-4239.875 #2509.E4 -4340 9465!-4340 9465[#FFEEBB.0F #24EB.3E -4502 9439.5!-4502 9439.5[#FFED5D.4F #24B8.B2 -5042 9384!-5042 9384[-5327 9366 -5583 9481!-5583 9481|-5347 10078
!-5347 10078|-4665 9805"/>
                    <Edge cubics="!-4005 -10749(;-3969,-10747 -3934,-10745 -3898,-10743q-4005 -10749 -3898 -10743);"/>
                    <Edge cubics="!1992 -10080(;2035,-10078 2077,-10076 2120,-10074q1992 -10080 2120 -10074);"/>
                    <Edge cubics="!2081 -9758(;2080,-9716 2080,-9674 2080,-9632q2081 -9758 2080 -9632);"/>
                    <Edge cubics="!-895 -10149(;-667,-10112 -440,-10072 -214,-10029q-895 -10149Q-553 -10093q-214 -10029);"/>
                    <Edge cubics="!530 -9921(;767,-9895 1003,-9869 1240,-9843q530 -9921Q885 -9882q1240 -9843);"/>
                    <Edge cubics="!-214 -10029(;33,-9982 281,-9946 530,-9921q-214 -10029Q157 -9958q530 -9921);"/>
                    <Edge cubics="!1975 -9768(;1975,-9768 2081,-9758 2081,-9758q1975 -9768 2081 -9758);"/>
                    <Edge cubics="!1975 -9768(;1975,-9768 1992,-10080 1992,-10080q1975 -9768 1992 -10080);"/>
                    <Edge cubics="!1240 -9843(;1485,-9818 1730,-9793 1975,-9768q1240 -9843Q1607 -9806q1975 -9768);"/>
                    <Edge cubics="!-3850 -10053(;-3855,-10126 -3861,-10198 -3867,-10271q-3850 -10053Q-3858 -10162q-3867 -10271);"/>
                    <Edge cubics="!-3867 -10271(;-3867,-10271 -3956,-10280 -3956,-10280q-3867 -10271 -3956 -10280);"/>
                    <Edge cubics="!-3956 -10280(;-3956,-10280 -3925,-10438 -3925,-10438q-3956 -10280 -3925 -10438);"/>
                    <Edge cubics="!-3925 -10438(;-3925,-10438 -3878,-10431 -3878,-10431q-3925 -10438 -3878 -10431);"/>
                    <Edge cubics="!-3878 -10431(;-3569,-10386 -3260,-10349 -2950,-10322q-3878 -10431Q-3415 -10363q-2950 -10322);"/>
                    <Edge cubics="!-4003 -10120(;-4016,-10329 -4017,-10539 -4005,-10749q-4003 -10120Q-4023 -10434q-4005 -10749);"/>
                    <Edge cubics="!-3898 -10743(;-3898,-10743 -3878,-10431 -3878,-10431q-3898 -10743 -3878 -10431);"/>
                    <Edge cubics="!-2950 -10322(;-2606,-10291 -2262,-10268 -1919,-10252q-2950 -10322Q-2434 -10276q-1919 -10252);"/>
                    <Edge cubics="!-3983 -6758(;-3936,-7033 -3901,-7311 -3879,-7592q-3983 -6758Q-3912 -7171q-3879 -7592);"/>
                    <Edge cubics="!-3986 -6048(;-3833,-6596 -3751,-7156 -3740,-7728q-3986 -6048Q-3756 -6870q-3740 -7728);"/>
                    <Edge cubics="!-4188 -5883(;-4103,-6170 -4034,-6462 -3983,-6758q-4188 -5883Q-4060 -6314q-3983 -6758);"/>
                    <Edge cubics="!-3740 -7728(;-3731,-8195 -3745,-8663 -3780,-9131q-3740 -7728Q-3727 -8429q-3780 -9131);"/>
                    <Edge cubics="!-3879 -7592(;-3843,-8047 -3850,-8502 -3901,-8956q-3879 -7592Q-3825 -8275q-3901 -8956);"/>
                    <Edge cubics="!-4257 -4792(;-4240,-4941 -4219,-5088 -4193,-5234q-4257 -4792Q-4232 -5015q-4193 -5234);"/>
                    <Edge cubics="!-4193 -5234(;-4176,-5327 -4156,-5418 -4132,-5507q-4193 -5234Q-4168 -5374q-4132 -5507);"/>
                    <Edge cubics="!-4132 -5507(;-4111,-5589 -4089,-5672 -4066,-5755q-4132 -5507Q-4100 -5630q-4066 -5755);"/>
                    <Edge cubics="!-4423 -4453(;-4420,-4636 -4405,-4819 -4380,-5002q-4423 -4453Q-4418 -4728q-4380 -5002);"/>
                    <Edge cubics="!-4132 -2573(;-4132,-2573 -4205,-2576 -4205,-2576q-4132 -2573 -4205 -2576);"/>
                    <Edge cubics="!-4352 -2364(;-4342,-2425 -4342,-2487 -4351,-2551q-4352 -2364Q-4337 -2455q-4351 -2551);"/>
                    <Edge cubics="!-4232 -2046(;-4232,-2046 -4103,-2049 -4103,-2049q-4232 -2046 -4103 -2049);"/>
                    <Edge cubics="!-4103 -2049(;-4169,-2223 -4179,-2398 -4132,-2573q-4103 -2049Q-4202 -2310q-4132 -2573);"/>
                    <Edge cubics="!-4351 -2551(;-4407,-2924 -4434,-3299 -4432,-3676q-4351 -2551Q-4435 -3111q-4432 -3676);"/>
                    <Edge cubics="!-4205 -2576(;-4322,-3313 -4339,-4052 -4257,-4792q-4205 -2576Q-4380 -3682q-4257 -4792);"/>
                    <Edge cubics="!-4432 -3676(;-4431,-3934 -4428,-4193 -4423,-4453q-4432 -3676Q-4430 -4063q-4423 -4453);"/>
                    <Edge cubics="!-4066 -5755(;-4040,-5851 -4013,-5949 -3986,-6048q-4066 -5755Q-4027 -5899q-3986 -6048);"/>
                    <Edge cubics="!-4380 -5002(;-4338,-5300 -4274,-5594 -4188,-5883q-4380 -5002Q-4317 -5449q-4188 -5883);"/>
                    <Edge cubics="!-4499 -1368(;-4455,-1701 -4406,-2033 -4352,-2364q-4499 -1368Q-4433 -1867q-4352 -2364);"/>
                    <Edge cubics="!2080 -9632(;2080,-9632 1959,-9640 1959,-9640q2080 -9632 1959 -9640);"/>
                    <Edge cubics="!1861 -6624(;1877,-6345 1906,-6065 1947,-5785q1861 -6624Q1885 -6205q1947 -5785);"/>
                    <Edge cubics="!1711 -7497(;1707,-7197 1714,-6896 1732,-6594q1711 -7497Q1705 -7047q1732 -6594);"/>
                    <Edge cubics="!1852 -7603(;1839,-7276 1842,-6950 1861,-6624q1852 -7603Q1832 -7113q1861 -6624);"/>
                    <Edge cubics="!1772 -8429(;1736,-8120 1716,-7809 1711,-7497q1772 -8429Q1718 -7965q1711 -7497);"/>
                    <Edge cubics="!1816 -5658(;1835,-5491 1858,-5326 1883,-5163q1816 -5658Q1845 -5408q1883 -5163);"/>
                    <Edge cubics="!1933 -3481(;1933,-3481 1890,-3483 1890,-3483q1933 -3481 1890 -3483);"/>
                    <Edge cubics="!1897 -2406(;1901,-2297 1909,-2189 1920,-2080q1897 -2406Q1903 -2243q1920 -2080);"/>
                    <Edge cubics="!1890 -3483(;1882,-3124 1884,-2765 1897,-2406q1890 -3483Q1878 -2945q1897 -2406);"/>
                    <Edge cubics="!2087 -3751(;2076,-3532 2058,-3314 2033,-3099q2087 -3751Q2070 -3422q2033 -3099);"/>
                    <Edge cubics="!2033 -3099(;2026,-3039 2023,-2979 2022,-2918q2033 -3099Q2023 -3009q2022 -2918);"/>
                    <Edge cubics="!2022 -2918(;2020,-2691 2031,-2464 2056,-2237q2022 -2918Q2019 -2578q2056 -2237);"/>
                    <Edge cubics="!2016 -5315(;2090,-4796 2114,-4274 2087,-3751q2016 -5315Q2127 -4536q2087 -3751);"/>
                    <Edge cubics="!1959 -9640(;1882,-9238 1819,-8834 1772,-8429q1959 -9640Q1843 -9037q1772 -8429);"/>
                    <Edge cubics="!1732 -6594(;1751,-6279 1779,-5967 1816,-5658q1732 -6594Q1761 -6122q1816 -5658);"/>
                    <Edge cubics="!1883 -5163(;1931,-4857 1958,-4549 1965,-4238q1883 -5163Q1955 -4704q1965 -4238);"/>
                    <Edge cubics="!1965 -4238(;1970,-3985 1960,-3733 1933,-3481q1965 -4238Q1973 -3859q1933 -3481);"/>
                    <Edge cubics="!1920 -2080(;1929,-1996 1941,-1914 1957,-1833q1920 -2080Q1933 -1954q1957 -1833);"/>
                    <Edge cubics="!2058 -9343(;1945,-8770 1876,-8190 1852,-7603q2058 -9343Q1888 -8483q1852 -7603);"/>
                    <Edge cubics="!1947 -5785(;1970,-5630 1993,-5473 2016,-5315q1947 -5785Q1982 -5552q2016 -5315);"/>
                    <Edge cubics="!2006 -1617(;2043,-1466 2085,-1316 2131,-1167q2006 -1617Q2062 -1390q2131 -1167);"/>
                    <Edge cubics="!1957 -1833(;1972,-1761 1988,-1689 2006,-1617q1957 -1833Q1979 -1725q2006 -1617);"/>
                    <Edge cubics="!2056 -2237(;2100,-1830 2192,-1433 2333,-1046q2056 -2237Q2122 -1626q2333 -1046);"/>
                    <Edge cubics="!-1919 -10252(;-1574,-10243 -1232,-10208 -895,-10149q-1919 -10252Q-1401 -10238q-895 -10149);"/>
                    <Edge cubics="!-3780 -9131(;-3803,-9437 -3826,-9744 -3850,-10053q-3780 -9131Q-3814 -9590q-3850 -10053);"/>
                    <Edge cubics="!2120 -10074(;2127,-9829 2106,-9585 2058,-9343q2120 -10074Q2130 -9706q2058 -9343);"/>
                    <Edge cubics="!-3901 -8956(;-3945,-9344 -3979,-9732 -4003,-10120q-3901 -8956Q-3967 -9538q-4003 -10120);"/>
                    <Edge cubics="!-6105 5010(;-6080,5001 -6052,4993 -6024,4986q-6105 5010 -6024 4986);"/>
                    <Edge cubics="!-6024 4986(;-6022,5037 -6020,5089 -6018,5140q-6024 4986 -6018 5140);"/>
                    <Edge cubics="!-5707 2688(;-5687,2618 -5668,2547 -5649,2476q-5707 2688Q-5677 2583q-5649 2476);"/>
                    <Edge cubics="!-5806 4107(;-5795,4037 -5784,3969 -5775,3902q-5806 4107Q-5789 4002q-5775 3902);"/>
                    <Edge cubics="!-5775 3902(;-5764,3816 -5753,3732 -5743,3650q-5775 3902Q-5758 3773q-5743 3650);"/>
                    <Edge cubics="!-5743 3650(;-5736,3599 -5729,3547 -5722,3496q-5743 3650Q-5733 3573q-5722 3496);"/>
                    <Edge cubics="!-5722 3496(;-5717,3463 -5710,3429 -5703,3396q-5722 3496Q-5714 3446q-5703 3396);"/>
                    <Edge cubics="!-5950 4088(;-5931,3967 -5914,3847 -5899,3728q-5950 4088Q-5922 3907q-5899 3728);"/>
                    <Edge cubics="!-5899 3728(;-5888,3637 -5876,3546 -5865,3455q-5899 3728Q-5882 3591q-5865 3455);"/>
                    <Edge cubics="!-5865 3455(;-5857,3392 -5848,3329 -5838,3267q-5865 3455Q-5853 3360q-5838 3267);"/>
                    <Edge cubics="!-5703 3396(;-5638,3087 -5567,2780 -5491,2473q-5703 3396Q-5605 2933q-5491 2473);"/>
                    <Edge cubics="!-5838 3267(;-5805,3072 -5762,2879 -5707,2688q-5838 3267Q-5789 2975q-5707 2688);"/>
                    <Edge cubics="!-6327 5098(;-6265,4903 -6188,4715 -6095,4534q-6327 5098Q-6234 4806q-6095 4534);"/>
                    <Edge cubics="!-7173 6090(;-6868,5676 -6483,5359 -6018,5140q-7173 6090Q-6715 5469q-6018 5140);"/>
                    <Edge cubics="!-6105 5010(;-5956,4726 -5857,4425 -5806,4107q-6105 5010Q-5882 4584q-5806 4107);"/>
                    <Edge cubics="!-6963 5582(;-6780,5383 -6568,5221 -6327,5098q-6963 5582Q-6688 5283q-6327 5098);"/>
                    <Edge cubics="!-6095 4534(;-6023,4394 -5975,4245 -5950,4088q-6095 4534Q-5987 4324q-5950 4088);"/>
                    <Edge cubics="!-2961 6341(;-3041,6336 -3120,6333 -3197,6330q-2961 6341Q-3081 6334q-3197 6330);"/>
                    <Edge cubics="!-3197 6330(;-3256,6326 -3314,6324 -3373,6323q-3197 6330Q-3285 6324q-3373 6323);"/>
                    <Edge cubics="!-2665 6360(;-2763,6353 -2862,6347 -2961,6341q-2665 6360Q-2812 6350q-2961 6341);"/>
                    <Edge cubics="!-4350 6615(;-4393,6630 -4436,6647 -4477,6667q-4350 6615Q-4415 6637q-4477 6667);"/>
                    <Edge cubics="!-4477 6667(;-4485,6672 -4492,6678 -4499,6685q-4477 6667Q-4489 6674q-4499 6685);"/>
                    <Edge cubics="!-4548 6497(;-4548,6497 -4563,6467 -4563,6467q-4548 6497 -4563 6467);"/>
                    <Edge cubics="!-4563 6467(;-4692,6463 -4790,6527 -4857,6658q-4563 6467Q-4757 6461q-4857 6658);"/>
                    <Edge cubics="!-4857 6658(;-4878,6698 -4899,6738 -4921,6777q-4857 6658Q-4888 6718q-4921 6777);"/>
                    <Edge cubics="!-4921 6777(;-4966,6858 -5000,6943 -5025,7032q-4921 6777Q-4988 6899q-5025 7032);"/>
                    <Edge cubics="!-4930 7408(;-4935,7499 -4911,7584 -4857,7661q-4930 7408Q-4938 7545q-4857 7661);"/>
                    <Edge cubics="!-3811 6338(;-4068,6348 -4314,6401 -4548,6497q-3811 6338Q-4197 6353q-4548 6497);"/>
                    <Edge cubics="!-5025 7032(;-5050,7122 -5066,7213 -5073,7304q-5025 7032Q-5063 7167q-5073 7304);"/>
                    <Edge cubics="!-4499 6685(;-4499,6685 -4628,6693 -4628,6693q-4499 6685 -4628 6693);"/>
                    <Edge cubics="!-4628 6693(;-4813,6900 -4914,7138 -4930,7408q-4628 6693Q-4906 7003q-4930 7408);"/>
                    <Edge cubics="!-4857 7661(;-4756,7804 -4636,7928 -4497,8035q-4857 7661Q-4705 7875q-4497 8035);"/>
                    <Edge cubics="!-4508 8289(;-4361,8447 -4299,8632 -4323,8843q-4508 8289Q-4287 8526q-4323 8843);"/>
                    <Edge cubics="!-4392 8127(;-4366,8152 -4343,8179 -4322,8208q-4392 8127Q-4353 8165q-4322 8208);"/>
                    <Edge cubics="!-4322 8208(;-4251,8311 -4207,8424 -4188,8547q-4322 8208Q-4216 8362q-4188 8547);"/>
                    <Edge cubics="!-4323 8843(;-4340,8994 -4376,9139 -4431,9278q-4323 8843Q-4349 9069q-4431 9278);"/>
                    <Edge cubics="!-3373 6323(;-3518,6322 -3664,6327 -3811,6338q-3373 6323Q-3591 6321q-3811 6338);"/>
                    <Edge cubics="!-4825 7992(;-4712,8084 -4607,8183 -4508,8289q-4825 7992Q-4656 8130q-4508 8289);"/>
                    <Edge cubics="!-3079 6468(;-3514,6435 -3937,6484 -4350,6615q-3079 6468Q-3731 6419q-4350 6615);"/>
                    <Edge cubics="!-4497 8035(;-4460,8063 -4425,8094 -4392,8127q-4497 8035Q-4441 8077q-4392 8127);"/>
                    <Edge cubics="!-7804 9863(;-7963,9774 -8091,9654 -8189,9502q-7804 9863Q-8042 9730q-8189 9502);"/>
                    <Edge cubics="!-7105 10011(;-7308,9923 -7507,9823 -7701,9710q-7105 10011Q-7410 9879q-7701 9710);"/>
                    <Edge cubics="!-7701 9710(;-7830,9635 -7940,9538 -8031,9421q-7701 9710Q-7895 9597q-8031 9421);"/>
                    <Edge cubics="!-8031 9421(;-8144,9276 -8212,9111 -8233,8927q-8031 9421Q-8201 9203q-8233 8927);"/>
                    <Edge cubics="!-8189 9502(;-8318,9302 -8385,9083 -8388,8845q-8189 9502Q-8383 9202q-8388 8845);"/>
                    <Edge cubics="!-8233 8927(;-8273,8584 -8238,8249 -8127,7920q-8233 8927Q-8293 8413q-8127 7920);"/>
                    <Edge cubics="!-8388 8845(;-8395,8305 -8290,7786 -8073,7287q-8388 8845Q-8399 8035q-8073 7287);"/>
                    <Edge cubics="!-6882 10227(;-6987,10218 -7087,10194 -7184,10155q-6882 10227Q-7039 10213q-7184 10155);"/>
                    <Edge cubics="!-5035 10225(;-5090,10233 -5146,10238 -5203,10240q-5035 10225Q-5118 10237q-5203 10240);"/>
                    <Edge cubics="!-6666 10122(;-6818,10109 -6964,10072 -7105,10011q-6666 10122Q-6894 10103q-7105 10011);"/>
                    <Edge cubics="!-7184 10155(;-7397,10072 -7603,9975 -7804,9863q-7184 10155Q-7503 10031q-7804 9863);"/>
                    <Edge cubics="!-8127 7920(;-7905,7261 -7587,6651 -7173,6090q-8127 7920Q-7794 6932q-7173 6090);"/>
                    <Edge cubics="!-8073 7287(;-7798,6656 -7428,6088 -6963,5582q-8073 7287Q-7661 6341q-6963 5582);"/>
                    <Edge cubics="!-5517 7600(;-5517,7561 -5518,7522 -5518,7482q-5517 7600 -5518 7482);"/>
                    <Edge cubics="!-5517 7600(;-5344,7633 -5176,7682 -5013,7747q-5517 7600Q-5258 7650q-5013 7747);"/>
                    <Edge cubics="!-5065 7553(;-5235,7494 -5386,7471 -5518,7482q-5065 7553Q-5320 7465q-5518 7482);"/>
                    <Edge cubics="!-5073 7304(;-5078,7387 -5076,7470 -5065,7553q-5073 7304Q-5081 7429q-5065 7553);"/>
                    <Edge cubics="!-5013 7747(;-4972,7842 -4910,7923 -4825,7992q-5013 7747Q-4952 7889q-4825 7992);"/>
                    <Edge cubics="!-5649 2476(;-5642,2451 -5636,2425 -5630,2400q-5649 2476Q-5639 2438q-5630 2400);"/>
                    <Edge cubics="!-5491 2473(;-5485,2449 -5479,2425 -5473,2400q-5491 2473Q-5482 2437q-5473 2400);"/>
                    <Edge cubics="!2131 -1167(;2198,-949 2273,-733 2354,-520q2131 -1167Q2232 -840q2354 -520);"/>
                    <Edge cubics="!2333 -1046(;2397,-869 2464,-694 2534,-520q2333 -1046Q2429 -781q2534 -520);"/>
                    <Edge cubics="!-4677 -205(;-4620,-515 -4561,-903 -4499,-1368q-4677 -205Q-4592 -670q-4499 -1368);"/>
                    <Edge cubics="!-4471 -609(;-4384,-1163 -4304,-1642 -4232,-2046q-4471 -609Q-4340 -1440q-4232 -2046);"/>
                    <Edge cubics="!-5334 1444(;-5243,1182 -5124,919 -4979,655q-5334 1444Q-5197 1051q-4979 655);"/>
                    <Edge cubics="!-5473 2400(;-5137,1421 -4908,813 -4785,576q-5473 2400Q-4969 931q-4785 576);"/>
                    <Edge cubics="!-5630 2400(;-5524,2024 -5425,1705 -5334,1444q-5630 2400Q-5471 1836q-5334 1444);"/>
                    <Edge cubics="!-260 6424(;-1327,6423 -2128,6401 -2665,6360q-260 6424Q-1860 6422q-2665 6360);"/>
                    <Edge cubics="!-260 6552(;-1465,6552 -2404,6524 -3079,6468q-260 6552Q-2067 6552q-3079 6468);"/>
                    <Edge cubics="!-4785 576(;-4663,339 -4558,-56 -4471,-609q-4785 576Q-4602 221q-4471 -609);"/>
                    <Edge cubics="!-4979 655(;-4834,392 -4734,105 -4677,-205q-4979 655Q-4762 260q-4677 -205);"/>
                    <Edge cubics="!-5763 9299(;-5720,9299 -5677,9299 -5634,9299q-5763 9299 -5634 9299);"/>
                    <Edge cubics="!-5042 9384(;-5232,9372 -5412,9404 -5583,9481q-5042 9384Q-5327 9366q-5583 9481);"/>
                    <Edge cubics="!-5634 9299(;-5634,9299 -5626,9329 -5626,9329q-5634 9299 -5626 9329);"/>
                    <Edge cubics="!-5770 9355(;-5770,9355 -5763,9299 -5763,9299q-5770 9355 -5763 9299);"/>
                    <Edge cubics="!-5852 9392(;-5852,9392 -5770,9355 -5770,9355q-5852 9392 -5770 9355);"/>
                    <Edge cubics="!-5866 9525(;-5866,9525 -5852,9392 -5852,9392q-5866 9525 -5852 9392);"/>
                    <Edge cubics="!-5721 9563(;-5721,9563 -5866,9525 -5866,9525q-5721 9563 -5866 9525);"/>
                    <Edge cubics="!-5583 9481(;-5583,9481 -5347,10078 -5347,10078q-5583 9481 -5347 10078);"/>
                    <Edge cubics="!-3877 9381(;-3882,9642 -4063,9824 -4422,9929q-3877 9381Q-3884 9772q-4422 9929);"/>
                    <Edge cubics="!-4431 9278(;-4432,9279 -4432,9280 -4432,9281q-4431 9278Q-4432 9279q-4432 9281);"/>
                    <Edge cubics="!-4140 9502(;-4207,9489 -4273,9476 -4340,9465q-4140 9502Q-4240 9482q-4340 9465);"/>
                    <Edge cubics="!-4340 9465(;-4394,9456 -4448,9447 -4502,9440q-4340 9465Q-4421 9451q-4502 9440);"/>
                    <Edge cubics="!-4268 9303(;-4138,9322 -4008,9348 -3877,9381q-4268 9303Q-4073 9332q-3877 9381);"/>
                    <Edge cubics="!-4188 8547(;-4148,8808 -4175,9060 -4268,9303q-4188 8547Q-4128 8939q-4268 9303);"/>
                    <Edge cubics="!-5383 10252(;-5383,10252 -5413,10258 -5413,10258q-5383 10252 -5413 10258);"/>
                    <Edge cubics="!-5413 10258(;-5414,10257 -5415,10255 -5416,10254q-5413 10258Q-5415 10256q-5416 10254);"/>
                    <Edge cubics="!-5203 10240(;-5263,10245 -5323,10249 -5383,10252q-5203 10240Q-5293 10247q-5383 10252);"/>
                    <Edge cubics="!-4422 9929(;-4490,9950 -4558,9971 -4626,9994q-4422 9929Q-4524 9960q-4626 9994);"/>
                    <Edge cubics="!-4502 9440(;-4681,9414 -4861,9395 -5042,9384q-4502 9440Q-4771 9401q-5042 9384);"/>
                    <Edge cubics="!-4626 9994(;-4727,10123 -4864,10200 -5035,10225q-4626 9994Q-4778 10188q-5035 10225);"/>
                    <Edge cubics="!-5511 10114(;-5610,9950 -5680,9766 -5721,9563q-5511 10114Q-5660 9868q-5721 9563);"/>
                    <Edge cubics="!-5626 9329(;-5231,9252 -4833,9236 -4432,9281q-5626 9329Q-5034 9213q-4432 9281);"/>
                    <Edge cubics="!-5511 10114(;-5896,10138 -6281,10141 -6666,10122q-5511 10114Q-6088 10150q-6666 10122);"/>
                    <Edge cubics="!-5416 10254(;-5905,10281 -6394,10272 -6882,10227q-5416 10254Q-6150 10294q-6882 10227);"/>
                    <Edge cubics="!3218 6408(;3218,6408 3086,6413 3086,6413q3218 6408 3086 6413);"/>
                    <Edge cubics="!3961 1884(;3962,1929 3963,1975 3964,2020q3961 1884 3964 2020);"/>
                    <Edge cubics="!3859 4765(;3859,4728 3859,4690 3859,4653q3859 4765 3859 4653);"/>
                    <Edge cubics="!4206 -67(;4267,-66 4327,-64 4388,-63q4206 -67Q4297 -65q4388 -63);"/>
                    <Edge cubics="!4388 -63(;4511,-57 4631,-45 4748,-27q4388 -63Q4572 -54q4748 -27);"/>
                    <Edge cubics="!4748 -27(;4840,-12 4933,8 5026,32q4748 -27Q4886 -4q5026 32);"/>
                    <Edge cubics="!4401 -198(;4821,-187 5226,-103 5615,54q4401 -198Q5031 -182q5615 54);"/>
                    <Edge cubics="!3039 -162(;3039,-162 2693,-105 2693,-105q3039 -162 2693 -105);"/>
                    <Edge cubics="!2693 -105(;2693,-105 2958,22 2958,22q2693 -105 2958 22);"/>
                    <Edge cubics="!3137 -370(;3162,-308 3182,-244 3197,-178q3137 -370Q3175 -277q3197 -178);"/>
                    <Edge cubics="!2958 22(;3290,-36 3631,-66 3980,-68q2958 22Q3456 -65q3980 -68);"/>
                    <Edge cubics="!3980 -68(;4055,-69 4131,-68 4206,-67q3980 -68Q4093 -69q4206 -67);"/>
                    <Edge cubics="!3197 -178(;3598,-202 4000,-209 4401,-198q3197 -178Q3799 -214q4401 -198);"/>
                    <Edge cubics="!2392 152(;2392,152 2337,136 2337,136q2392 152 2337 136);"/>
                    <Edge cubics="!2276 181(;2276,181 2392,152 2392,152q2276 181 2392 152);"/>
                    <Edge cubics="!2337 136(;2337,136 2276,181 2276,181q2337 136 2276 181);"/>
                    <Edge cubics="!1828 3062(;1897,2836 2034,2663 2241,2543q1828 3062Q1931 2723q2241 2543);"/>
                    <Edge cubics="!2241 2342(;2174,2371 2110,2407 2047,2449q2241 2342Q2141 2386q2047 2449);"/>
                    <Edge cubics="!2047 2449(;1977,2496 1915,2551 1862,2613q2047 2449Q1942 2520q1862 2613);"/>
                    <Edge cubics="!1862 2613(;1813,2669 1773,2732 1744,2801q1862 2613Q1788 2697q1744 2801);"/>
                    <Edge cubics="!1853 3483(;1793,3345 1785,3205 1828,3062q1853 3483Q1763 3276q1828 3062);"/>
                    <Edge cubics="!1744 2801(;1711,2882 1689,2966 1678,3053q1744 2801Q1694 2922q1678 3053);"/>
                    <Edge cubics="!1678 3053(;1644,3334 1697,3593 1836,3830q1678 3053Q1627 3475q1836 3830);"/>
                    <Edge cubics="!5128 4971(;5115,4937 5094,4911 5064,4892q5128 4971Q5109 4920q5064 4892);"/>
                    <Edge cubics="!5057 5188(;5084,5261 5100,5337 5105,5417q5057 5188Q5097 5297q5105 5417);"/>
                    <Edge cubics="!5105 5417(;5112,5522 5110,5627 5098,5732q5105 5417Q5116 5574q5098 5732);"/>
                    <Edge cubics="!5064 4892(;4895,4791 4714,4725 4521,4692q5064 4892Q4810 4741q4521 4692);"/>
                    <Edge cubics="!4851 4973(;4890,4988 4924,5009 4955,5036q4851 4973Q4909 4996q4955 5036);"/>
                    <Edge cubics="!4955 5036(;5002,5078 5036,5129 5057,5188q4955 5036Q5025 5099q5057 5188);"/>
                    <Edge cubics="!4353 4027(;4060,4084 3765,4121 3468,4139q4353 4027Q3913 4112q3468 4139);"/>
                    <Edge cubics="!3781 4263(;4265,4206 4742,4111 5212,3976q3781 4263Q4507 4178q5212 3976);"/>
                    <Edge cubics="!4521 4692(;4301,4652 4080,4639 3859,4653q4521 4692Q4191 4632q3859 4653);"/>
                    <Edge cubics="!3859 4765(;4202,4776 4533,4845 4851,4973q3859 4765Q4374 4781q4851 4973);"/>
                    <Edge cubics="!2241 2543(;2522,2381 2821,2264 3140,2192q2241 2543Q2662 2300q3140 2192);"/>
                    <Edge cubics="!3140 2192(;3413,2128 3687,2071 3964,2020q3140 2192Q3549 2096q3964 2020);"/>
                    <Edge cubics="!3961 1884(;3361,1942 2788,2095 2241,2342q3961 1884Q3061 1971q2241 2342);"/>
                    <Edge cubics="!6057 271(;6193,353 6323,445 6446,548q6057 271Q6261 394q6446 548);"/>
                    <Edge cubics="!6488 859(;6640,1006 6756,1176 6837,1369q6488 859Q6716 1079q6837 1369);"/>
                    <Edge cubics="!6446 548(;6585,663 6702,797 6797,950q6446 548Q6655 720q6797 950);"/>
                    <Edge cubics="!6797 950(;6977,1243 7097,1558 7158,1896q6797 950Q7067 1389q7158 1896);"/>
                    <Edge cubics="!7023 2179(;7036,2406 6975,2612 6839,2795q7023 2179Q7043 2520q6839 2795);"/>
                    <Edge cubics="!7184 2197(;7183,2316 7163,2433 7126,2548q7184 2197Q7182 2376q7126 2548);"/>
                    <Edge cubics="!6293 3319(;6120,3436 5935,3535 5740,3614q6293 3319Q6033 3495q5740 3614);"/>
                    <Edge cubics="!5743 3805(;6000,3713 6239,3590 6461,3436q5743 3805Q6128 3667q6461 3436);"/>
                    <Edge cubics="!6982 3500(;7030,3510 7074,3530 7114,3559q6982 3500Q7054 3515q7114 3559);"/>
                    <Edge cubics="!7114 3559(;7161,3594 7205,3635 7244,3680q7114 3559Q7185 3612q7244 3680);"/>
                    <Edge cubics="!6620 3310(;6852,3280 7063,3327 7252,3450q6620 3310Q6968 3265q7252 3450);"/>
                    <Edge cubics="!6839 2795(;6687,3001 6505,3176 6293,3319q6839 2795Q6611 3104q6293 3319);"/>
                    <Edge cubics="!6461 3436(;6638,3437 6812,3458 6982,3500q6461 3436Q6727 3437q6982 3500);"/>
                    <Edge cubics="!7126 2548(;7029,2849 6860,3103 6620,3310q7126 2548Q6980 2999q6620 3310);"/>
                    <Edge cubics="!7752 4228(;7788,4331 7824,4435 7859,4538q7752 4228Q7806 4383q7859 4538);"/>
                    <Edge cubics="!7859 4538(;7890,4629 7920,4719 7950,4810q7859 4538Q7905 4674q7950 4810);"/>
                    <Edge cubics="!7950 4810(;7983,4911 8014,5013 8042,5114q7950 4810Q8000 4962q8042 5114);"/>
                    <Edge cubics="!7916 5206(;8003,5499 8020,5794 7968,6091q7916 5206Q8046 5645q7968 6091);"/>
                    <Edge cubics="!7531 4154(;7682,4498 7810,4849 7916,5206q7531 4154Q7757 4670q7916 5206);"/>
                    <Edge cubics="!8042 5114(;8120,5397 8150,5685 8131,5977q8042 5114Q8159 5539q8131 5977);"/>
                    <Edge cubics="!7244 3680(;7297,3743 7345,3809 7388,3879q7244 3680Q7324 3774q7388 3879);"/>
                    <Edge cubics="!7388 3879(;7442,3968 7490,4059 7531,4154q7388 3879Q7469 4012q7531 4154);"/>
                    <Edge cubics="!7252 3450(;7335,3505 7406,3574 7463,3657q7252 3450Q7377 3532q7463 3657);"/>
                    <Edge cubics="!7463 3657(;7585,3832 7681,4023 7752,4228q7463 3657Q7646 3920q7752 4228);"/>
                    <Edge cubics="!6837 1369(;6945,1629 7007,1899 7023,2179q6837 1369Q6999 1759q7023 2179);"/>
                    <Edge cubics="!7158 1896(;7176,1996 7185,2096 7184,2197q7158 1896Q7185 2046q7184 2197);"/>
                    <Edge cubics="!5026 32(;5587,182 6075,458 6488,859q5026 32Q5868 257q6488 859);"/>
                    <Edge cubics="!5740 3614(;5290,3797 4828,3934 4353,4027q5740 3614Q5065 3888q4353 4027);"/>
                    <Edge cubics="!5212 3976(;5390,3924 5567,3867 5743,3805q5212 3976Q5479 3898q5743 3805);"/>
                    <Edge cubics="!5615 54(;5769,115 5916,188 6057,271q5615 54Q5846 146q6057 271);"/>
                    <Edge cubics="!8045 6446(;7999,6597 7943,6746 7877,6892q8045 6446Q7976 6673q7877 6892);"/>
                    <Edge cubics="!7792 6659(;7667,6931 7533,7199 7390,7463q7792 6659Q7605 7067q7390 7463);"/>
                    <Edge cubics="!7877 6892(;7747,7178 7597,7453 7428,7717q7877 6892Q7682 7321q7428 7717);"/>
                    <Edge cubics="!6139 8381(;6213,8376 6285,8364 6355,8347q6139 8381Q6250 8373q6355 8347);"/>
                    <Edge cubics="!6140 9440(;6085,9569 6022,9692 5949,9810q6140 9440Q6058 9633q5949 9810);"/>
                    <Edge cubics="!5949 9810(;5900,9889 5843,9962 5779,10029q5949 9810Q5875 9928q5779 10029);"/>
                    <Edge cubics="!6355 8347(;6361,8726 6289,9091 6140,9440q6355 8347Q6364 8916q6140 9440);"/>
                    <Edge cubics="!6477 8314(;6517,8753 6449,9172 6273,9573q6477 8314Q6537 8972q6273 9573);"/>
                    <Edge cubics="!7390 7463(;7339,7556 7275,7638 7197,7709q7390 7463Q7314 7603q7197 7709);"/>
                    <Edge cubics="!7197 7709(;6975,7908 6722,8056 6439,8153q7197 7709Q6864 8007q6439 8153);"/>
                    <Edge cubics="!7428 7717(;7379,7794 7319,7859 7246,7913q7428 7717Q7355 7832q7246 7913);"/>
                    <Edge cubics="!7246 7913(;7011,8091 6754,8225 6477,8314q7246 7913Q6893 8180q6477 8314);"/>
                    <Edge cubics="!6273 9573(;6189,9763 6083,9939 5955,10101q6273 9573Q6147 9858q5955 10101);"/>
                    <Edge cubics="!4716 7008(;4868,6796 4994,6572 5093,6335q4716 7008Q4944 6690q5093 6335);"/>
                    <Edge cubics="!4664 6726(;4523,6891 4443,7081 4424,7294q4664 6726Q4453 6974q4424 7294);"/>
                    <Edge cubics="!3386 6483(;3370,6484 3355,6482 3340,6477q3386 6483Q3362 6484q3340 6477);"/>
                    <Edge cubics="!3678 7080(;3625,6974 3569,6869 3510,6764q3678 7080Q3599 6921q3510 6764);"/>
                    <Edge cubics="!3510 6764(;3467,6687 3402,6638 3316,6617q3510 6764Q3445 6649q3316 6617);"/>
                    <Edge cubics="!3689 6688(;3622,6568 3521,6500 3386,6483q3689 6688Q3588 6508q3386 6483);"/>
                    <Edge cubics="!2676 6277(;2623,6283 2571,6287 2518,6289q2676 6277Q2597 6286q2518 6289);"/>
                    <Edge cubics="!3218 6408(;3055,6292 2874,6248 2676,6277q3218 6408Q2973 6234q2676 6277);"/>
                    <Edge cubics="!3059 6568(;2896,6546 2737,6507 2581,6452q3059 6568Q2815 6535q2581 6452);"/>
                    <Edge cubics="!3878 7709(;3921,7512 3916,7317 3865,7124q3878 7709Q3942 7413q3865 7124);"/>
                    <Edge cubics="!3865 7124(;3825,6972 3766,6827 3689,6688q3865 7124Q3805 6896q3689 6688);"/>
                    <Edge cubics="!3340 6477(;3255,6456 3171,6434 3086,6413q3340 6477Q3213 6445q3086 6413);"/>
                    <Edge cubics="!3744 7615(;3786,7429 3764,7251 3678,7080q3744 7615Q3807 7336q3678 7080);"/>
                    <Edge cubics="!3316 6617(;3230,6598 3144,6582 3059,6568q3316 6617Q3187 6589q3059 6568);"/>
                    <Edge cubics="!3557 9011(;3575,8813 3616,8620 3679,8432q3557 9011Q3584 8714q3679 8432);"/>
                    <Edge cubics="!3443 8708(;3472,8581 3506,8457 3545,8335q3443 8708Q3486 8518q3545 8335);"/>
                    <Edge cubics="!3690 9973(;3627,9898 3577,9816 3538,9727q3690 9973Q3596 9860q3538 9727);"/>
                    <Edge cubics="!3646 9540(;3570,9372 3540,9196 3557,9011q3646 9540Q3532 9288q3557 9011);"/>
                    <Edge cubics="!3538 9727(;3395,9398 3364,9059 3443,8708q3538 9727Q3324 9234q3443 8708);"/>
                    <Edge cubics="!5201 8331(;5302,8364 5407,8383 5514,8386q5201 8331Q5353 8381q5514 8386);"/>
                    <Edge cubics="!3679 8432(;3759,8195 3825,7954 3878,7709q3679 8432Q3799 8076q3878 7709);"/>
                    <Edge cubics="!3545 8335(;3623,8096 3689,7856 3744,7615q3545 8335Q3662 7976q3744 7615);"/>
                    <Edge cubics="!2263 6301(;2156,6308 2050,6321 1943,6338q2263 6301Q2103 6312q1943 6338);"/>
                    <Edge cubics="!1943 6338(;1869,6352 1795,6366 1721,6380q1943 6338Q1832 6359q1721 6380);"/>
                    <Edge cubics="!2457 6440(;2309,6445 2161,6461 2013,6486q2457 6440Q2235 6448q2013 6486);"/>
                    <Edge cubics="!2013 6486(;1958,6494 1904,6499 1850,6502q2013 6486Q1931 6498q1850 6502);"/>
                    <Edge cubics="!5622 10160(;5557,10205 5490,10245 5421,10280q5622 10160Q5524 10227q5421 10280);"/>
                    <Edge cubics="!5658 10354(;5562,10407 5461,10450 5355,10482q5658 10354Q5514 10434q5355 10482);"/>
                    <Edge cubics="!5355 10482(;5245,10517 5132,10543 5016,10562q5355 10482Q5190 10534q5016 10562);"/>
                    <Edge cubics="!2518 6289(;2433,6291 2348,6295 2263,6301q2518 6289Q2391 6292q2263 6301);"/>
                    <Edge cubics="!3880 10180(;3814,10116 3751,10047 3690,9973q3880 10180Q3781 10084q3690 9973);"/>
                    <Edge cubics="!2581 6452(;2548,6439 2507,6435 2457,6440q2581 6452Q2532 6432q2457 6440);"/>
                    <Edge cubics="!6439 8153(;6127,8260 5809,8287 5484,8232q6439 8153Q5971 8314q5484 8232);"/>
                    <Edge cubics="!5514 8386(;5723,8395 5932,8393 6139,8381q5514 8386Q5828 8399q6139 8381);"/>
                    <Edge cubics="!5779 10029(;5731,10078 5679,10122 5622,10160q5779 10029Q5707 10103q5622 10160);"/>
                    <Edge cubics="!5955 10101(;5873,10204 5774,10289 5658,10354q5955 10101Q5832 10256q5658 10354);"/>
                    <Edge cubics="!7968 6091(;7934,6288 7875,6478 7792,6659q7968 6091Q7917 6387q7792 6659);"/>
                    <Edge cubics="!5093 6335(;5283,5881 5295,5426 5128,4971q5093 6335Q5378 5654q5128 4971);"/>
                    <Edge cubics="!5098 5732(;5054,6108 4909,6439 4664,6726q5098 5732Q5032 6296q4664 6726);"/>
                    <Edge cubics="!8131 5977(;8121,6136 8092,6293 8045,6446q8131 5977Q8116 6216q8045 6446);"/>
                    <Edge cubics="!1721 6380(;1564,6390 1408,6398 1251,6405q1721 6380Q1486 6395q1251 6405);"/>
                    <Edge cubics="!1850 6502(;1651,6515 1451,6525 1251,6533q1850 6502Q1551 6521q1251 6533);"/>
                    <Edge cubics="!2275 3238(;2318,3240 2360,3241 2403,3243q2275 3238 2403 3243);"/>
                    <Edge cubics="!2403 3243(;2403,3254 2403,3265 2403,3275q2403 3243 2403 3275);"/>
                    <Edge cubics="!2194 3416(;2174,3412 2153,3408 2133,3404q2194 3416 2133 3404);"/>
                    <Edge cubics="!2133 3404(;2133,3365 2133,3326 2133,3287q2133 3404 2133 3287);"/>
                    <Edge cubics="!2404 3421(;2404,3448 2403,3474 2403,3501q2404 3421 2403 3501);"/>
                    <Edge cubics="!2459 3416(;2440,3417 2422,3419 2404,3421q2459 3416Q2431 3418q2404 3421);"/>
                    <Edge cubics="!2747 3472(;2659,3417 2563,3398 2459,3416q2747 3472Q2615 3389q2459 3416);"/>
                    <Edge cubics="!2133 3287(;2133,3287 2275,3238 2275,3238q2133 3287 2275 3238);"/>
                    <Edge cubics="!2931 4321(;2905,4340 2877,4352 2846,4359q2931 4321Q2892 4349q2846 4359);"/>
                    <Edge cubics="!2846 4359(;2801,4367 2756,4366 2712,4355q2846 4359Q2778 4371q2712 4355);"/>
                    <Edge cubics="!2712 4355(;2712,4355 2700,4323 2700,4323q2712 4355 2700 4323);"/>
                    <Edge cubics="!2700 4323(;2423,4343 2152,4390 1889,4463q2700 4323Q2284 4353q1889 4463);"/>
                    <Edge cubics="!4894 7428(;4876,7414 4858,7401 4839,7388q4894 7428Q4867 7407q4839 7388);"/>
                    <Edge cubics="!4624 7293(;4693,7252 4766,7234 4844,7238q4624 7293Q4727 7232q4844 7238);"/>
                    <Edge cubics="!4844 7238(;4865,7240 4886,7242 4907,7244q4844 7238Q4875 7241q4907 7244);"/>
                    <Edge cubics="!4998 7509(;4963,7482 4928,7455 4894,7428q4998 7509Q4945 7469q4894 7428);"/>
                    <Edge cubics="!4876 8223(;4876,8223 4869,8189 4869,8189q4876 8223 4869 8189);"/>
                    <Edge cubics="!4164 7982(;4147,7995 4128,8007 4109,8018q4164 7982Q4138 8002q4109 8018);"/>
                    <Edge cubics="!4551 9834(;4492,9771 4419,9745 4333,9756q4551 9834Q4462 9739q4333 9756);"/>
                    <Edge cubics="!4333 9756(;4320,9758 4308,9760 4295,9762q4333 9756Q4314 9759q4295 9762);"/>
                    <Edge cubics="!4162 9621(;4461,9548 4662,9639 4767,9894q4162 9621Q4610 9512q4767 9894);"/>
                    <Edge cubics="!4869 8189(;4869,8189 3848,8141 3848,8141q4869 8189 3848 8141);"/>
                    <Edge cubics="!4670 10202(;4695,10058 4656,9935 4551,9834q4670 10202Q4708 9986q4551 9834);"/>
                    <Edge cubics="!4767 9894(;4818,10017 4828,10156 4797,10310q4767 9894Q4843 10079q4797 10310);"/>
                    <Edge cubics="!3781 10717(;3722,10738 3660,10748 3595,10749q3781 10717Q3693 10748q3595 10749);"/>
                    <Edge cubics="!3595 10749(;3592,10666 3617,10594 3670,10532q3595 10749Q3591 10625q3670 10532);"/>
                    <Edge cubics="!5081 8088(;5256,7877 5229,7684 4998,7509q5081 8088Q5344 7771q4998 7509);"/>
                    <Edge cubics="!4907 7244(;5324,7441 5436,7744 5241,8152q4907 7244Q5533 7540q5241 8152);"/>
                    <Edge cubics="!3848 8141(;3973,7898 4162,7664 4417,7441q3848 8141Q4035 7776q4417 7441);"/>
                    <Edge cubics="!2033 3751(;1958,3676 1898,3587 1853,3483q2033 3751Q1921 3639q1853 3483);"/>
                    <Edge cubics="!2403 3501(;2305,3607 2227,3727 2169,3862q2403 3501Q2256 3660q2169 3862);"/>
                    <Edge cubics="!2033 3751(;2077,3639 2131,3527 2194,3416q2033 3751Q2099 3583q2194 3416);"/>
                    <Edge cubics="!3468 4139(;3323,4150 3181,4149 3042,4136q3468 4139Q3251 4156q3042 4136);"/>
                    <Edge cubics="!2989 4274(;3253,4295 3517,4292 3781,4263q2989 4274Q3385 4306q3781 4263);"/>
                    <Edge cubics="!2881 4129(;2882,4124 2883,4120 2884,4115q2881 4129Q2882 4122q2884 4115);"/>
                    <Edge cubics="!2989 4274(;2971,4291 2952,4307 2931,4321q2989 4274Q2962 4300q2931 4321);"/>
                    <Edge cubics="!2105 4046(;2086,4113 2072,4184 2062,4257q2105 4046Q2077 4147q2062 4257);"/>
                    <Edge cubics="!1889 4463(;1892,4295 1917,4129 1962,3964q1889 4463Q1894 4211q1962 3964);"/>
                    <Edge cubics="!4417 7441(;4418,7440 4419,7440 4420,7439q4417 7441Q4418 7440q4420 7439);"/>
                    <Edge cubics="!4424 7294(;4419,7343 4418,7391 4420,7439q4424 7294Q4417 7367q4420 7439);"/>
                    <Edge cubics="!4839 7388(;4760,7466 4679,7543 4596,7618q4839 7388Q4720 7505q4596 7618);"/>
                    <Edge cubics="!4596 7618(;4553,7656 4511,7694 4468,7732q4596 7618Q4532 7675q4468 7732);"/>
                    <Edge cubics="!4584 7318(;4597,7309 4610,7301 4624,7293q4584 7318Q4603 7305q4624 7293);"/>
                    <Edge cubics="!4584 7318(;4603,7207 4647,7104 4716,7008q4584 7318Q4613 7152q4716 7008);"/>
                    <Edge cubics="!2403 3275(;2936,3275 3149,3562 3042,4136q2403 3275Q3202 3275q3042 4136);"/>
                    <Edge cubics="!2884 4115(;2926,3884 2880,3669 2747,3472q2884 4115Q2947 3768q2747 3472);"/>
                    <Edge cubics="!2169 3862(;2144,3921 2122,3982 2105,4046q2169 3862Q2131 3950q2105 4046);"/>
                    <Edge cubics="!1836 3830(;1868,3884 1910,3929 1962,3964q1836 3830Q1884 3911q1962 3964);"/>
                    <Edge cubics="!5241 8152(;5239,8157 5237,8162 5234,8167q5241 8152Q5238 8159q5234 8167);"/>
                    <Edge cubics="!4950 8226(;4950,8226 4876,8223 4876,8223q4950 8226 4876 8223);"/>
                    <Edge cubics="!4950 8226(;5030,8267 5114,8302 5201,8331q4950 8226Q5070 8288q5201 8331);"/>
                    <Edge cubics="!4797 10310(;4736,10337 4675,10363 4614,10389q4797 10310Q4706 10350q4614 10389);"/>
                    <Edge cubics="!3889 10188(;3886,10185 3883,10183 3880,10180q3889 10188Q3884 10184q3880 10180);"/>
                    <Edge cubics="!4077 10117(;4050,10172 4025,10229 4003,10286q4077 10117Q4036 10200q4003 10286);"/>
                    <Edge cubics="!4003 10286(;3978,10347 3957,10410 3938,10475q4003 10286Q3966 10378q3938 10475);"/>
                    <Edge cubics="!5016 10562(;4789,10594 4573,10570 4366,10491q5016 10562Q4676 10610q4366 10491);"/>
                    <Edge cubics="!5421 10280(;5154,10414 4885,10450 4614,10389q5421 10280Q5020 10481q4614 10389);"/>
                    <Edge cubics="!4295 9762(;4210,9874 4138,9992 4077,10117q4295 9762Q4168 9930q4077 10117);"/>
                    <Edge cubics="!3958 10005(;3958,10005 4162,9621 4162,9621q3958 10005 4162 9621);"/>
                    <Edge cubics="!5484 8232(;5397,8217 5313,8196 5234,8167q5484 8232Q5353 8210q5234 8167);"/>
                    <Edge cubics="!3670 10532(;3760,10427 3833,10313 3889,10188q3670 10532Q3805 10375q3889 10188);"/>
                    <Edge cubics="!4366 10491(;4172,10570 3977,10645 3781,10717q4366 10491Q4075 10609q3781 10717);"/>
                    <Edge cubics="!3958 10005(;3828,9869 3724,9714 3646,9540q3958 10005Q3763 9801q3646 9540);"/>
                    <Edge cubics="!4468 7732(;4369,7817 4268,7901 4164,7982q4468 7732Q4320 7860q4164 7982);"/>
                    <Edge cubics="!3127 -395(;3130,-386 3134,-378 3137,-370q3127 -395Q3132 -382q3137 -370);"/>
                    <Edge cubics="!2945 -395(;2975,-317 3006,-239 3039,-162q2945 -395Q2990 -278q3039 -162);"/>
                    <Edge cubics="!2945 -395(;2945,-395 3127,-395 3127,-395q2945 -395 3127 -395);"/>
                    <Edge cubics="!2062 4257(;2062,4257 2881,4129 2881,4129q2062 4257 2881 4129);"/>
                    <Edge cubics="!5006 8094(;5006,8094 5081,8088 5081,8088q5006 8094 5081 8088);"/>
                    <Edge cubics="!5000 8046(;5000,8046 5006,8094 5006,8094q5000 8046 5006 8094);"/>
                    <Edge cubics="!4109 8018(;4109,8018 5000,8046 5000,8046q4109 8018 5000 8046);"/>
                    <Edge cubics="!3938 10475(;3938,10475 4670,10202 4670,10202q3938 10475 4670 10202);"/>
                    <Edge cubics="!397 6552(;397,6552 397,6424 397,6424q397 6552 397 6424);"/>
                    <Edge cubics="!397 6424(;397,6424 397,-395 397,-395q397 6424 397 -395);"/>
                    <Edge cubics="!1251 6533(;966,6544 682,6551 397,6552q1251 6533Q824 6550q397 6552);"/>
                    <Edge cubics="!1251 6405(;966,6417 682,6423 397,6424q1251 6405Q824 6423q397 6424);"/>
                    <Edge cubics="!2354 -520(;2370,-478 2386,-436 2403,-395q2354 -520Q2378 -457q2403 -395);"/>
                    <Edge cubics="!2585 -395(;2585,-395 2945,-395 2945,-395q2585 -395 2945 -395);"/>
                    <Edge cubics="!2534 -520(;2551,-478 2568,-436 2585,-395q2534 -520Q2559 -457q2585 -395);"/>
                    <Edge cubics="!2403 -395(;2403,-395 2585,-395 2585,-395q2403 -395 2585 -395);"/>
                    <Edge cubics="!397 -395(;397,-395 2403,-395 2403,-395q397 -395 2403 -395);"/>
                    <Edge cubics="!-145 6552(;-145,6552 -145,6424 -145,6424q-145 6552 -145 6424);"/>
                    <Edge cubics="!-145 6424(;-183,6424 -221,6424 -260,6424q-145 6424Q-202 6424q-260 6424);"/>
                    <Edge cubics="!-145 6552(;-183,6552 -221,6552 -260,6552q-145 6552Q-202 6552q-260 6552);"/>
                    <Edge cubics="!-4665 9805(;-4665,9805 -4140,9502 -4140,9502q-4665 9805 -4140 9502);"/>
                    <Edge cubics="!-5347 10078(;-5347,10078 -4665,9805 -4665,9805q-5347 10078 -4665 9805);"/>
                    <Edge cubics="!-145 -395(;-145,-395 397,-395 397,-395q-145 -395 397 -395);"/>
                    <Edge cubics="!-145 6424(;-145,6424 -145,-395 -145,-395q-145 6424 -145 -395);"/>
                  </edges>
                </DOMShape>
              </elements>
            </DOMFrame>
          </frames>
        </DOMLayer>
      </layers>
    </DOMTimeline>
  </timeline>
</DOMSymbolItem>